{
  "default": {
    "King": {
      "Male": "King",
      "Female": "Queen"
    },
    "Duke": {
      "Male": "Duke",
      "Female": "Duchess"
    },
    "Count": {
      "Male": "Count",
      "Female": "Countess"
    },
    "Baron": {
      "Male": "Baron",
      "Female": "Baroness"
    },
    "Governor": {
      "Male": "Governor",
      "Female": "Governess"
    }
  },
  "vlandia": {
    "King": {
      "Male": "King",
      "Female": "Queen"
    },
    "Duke": {
      "Male": "Duke",
      "Female": "Duchess"
    },
    "Count": {
      "Male": "Count",
      "Female": "Countess"
    },
    "Baron": {
      "Male": "Baron",
      "Female": "Baroness"
    },
    "Governor": {
      "Male": "Mayor",
      "Female": "Mayor"
    }
  },
  "empire": {
    "King": {
      "Male": "Emperor",
      "Female": "Empress"
    },
    "Duke": {
      "Male": "Doux",
      "Female": "Doux"
    },
    "Count": {
      "Male": "Catepan",
      "Female": "Kyria"
    },
    "Baron": {
      "Male": "Strategos",
      "Female": "Kyria"
    },
    "Governor": {
      "Male": "Kephale",
      "Female": "Kephale"
    }
  },
  "sturgia": {
    "King": {
      "Male": "Grand Prince",
      "Female": "Grand Princess"
    },
    "Duke": {
      "Male": "Prince",
      "Female": "Princess"
    },
    "Count": {
      "Male": "Jarl",
      "Female": "Jarl"
    },
    "Baron": {
      "Male": "Boyar",
      "Female": "Boyarina"
    },
    "Governor": {
      "Male": "Thane",
      "Female": "Thane"
    }
  },
  "battania": {
    "King": {
      "Male": "High King",
      "Female": "High Queen"
    },
    "Duke": {
      "Male": "Mormaer",
      "Female": "Bantiarna"
    },
    "Count": {
      "Male": "High Chief",
      "Female": "High Chieftess"
    },
    "Baron": {
      "Male": "Chief",
      "Female": "Chieftess"
    },
    "Governor": {
      "Male": "Corono",
      "Female": "Corono"
    }
  },
  "khuzait": {
    "King": {
      "Male": "Khagan",
      "Female": "Khatun"
    },
    "Duke": {
      "Male": "Baghatur",
      "Female": "Bekhi"
    },
    "Count": {
      "Male": "Khan",
      "Female": "Khanum"
    },
    "Baron": {
      "Male": "Bey",
      "Female": "Begum"
    },
    "Governor": {
      "Male": "Governor",
      "Female": "Governess"
    }
  },
  "aserai": {
    "King": {
      "Male": "Sultan",
      "Female": "Sultana"
    },
    "Duke": {
      "Male": "Prince",
      "Female": "Princess"
    },
    "Count": {
      "Male": "Emir",
      "Female": "Emira"
    },
    "Baron": {
      "Male": "Sheikh",
      "Female": "Sheikha"
    },
    "Governor": {
      "Male": "Governor",
      "Female": "Governess"
    }
  }
}